error_generator/__init__.py
error_generator/abbreviations.py
error_generator/base.py
error_generator/dob.py
error_generator/edit_distance.py
error_generator/error_record.py
error_generator/file_based.py
error_generator/main.py
error_generator/nicknames.py
error_generator/swaps.py
error_generator-0.2.2.dist-info/METADATA
error_generator-0.2.2.dist-info/WHEEL
error_generator-0.2.2.dist-info/entry_points.txt
error_generator-0.2.2.dist-info/top_level.txt
error_generator-0.2.2.dist-info/RECORD
