Metadata-Version: 2.4
Name: error-generator
Version: 0.2.2
Summary: A package for generating realistic errors in data
Home-page: https://github.com/yourusername/error-generator
Author: Joshua Immanuel
Author-email: Joshua Immanuel <joshua9@tamu.edu>
Requires-Python: >=3.6
Requires-Dist: pandas
Requires-Dist: numpy
Dynamic: author
Dynamic: home-page
Dynamic: requires-python
